{
  "appPageId" : "65550390-4173-4ae0-8693-b0aeef889a0d",
  "componentName" : "siteforce:sldsOneColLayout",
  "id" : "046ab72c-92bb-4f4b-9a9e-2367b03545d2",
  "label" : "Account Management",
  "regions" : [ {
    "id" : "ccd55b41-b4b0-43bf-85a0-3e3b38401ff7",
    "regionName" : "header",
    "type" : "region"
  }, {
    "components" : [ {
      "componentAttributes" : {
        "tabsetConfig" : {
          "UUID" : "b60a29ee-39cf-4be1-9054-9ba95c439c34",
          "activeTab" : "tab1",
          "useOverflowMenu" : false,
          "tabs" : [ {
            "UUID" : "38225c3a-21eb-4b67-b93b-0dd6ce20555e",
            "tabName" : "Members",
            "tabKey" : "tab1",
            "locked" : false,
            "allowGuestUser" : false,
            "seedComponents" : [ {
              "fqn" : "forceCommunity:relatedList",
              "attributes" : {
                "parentRecordId" : "{!CurrentUser.effectiveAccountId}",
                "relatedListName" : "Users",
                "customTitle" : "Members",
                "showCustomTitle" : "true",
                "showBreadCrumbs" : "false",
                "showRowNumbers" : "false",
                "showManualRefreshButton" : "false"
              }
            } ]
          }, {
            "UUID" : "4c6fb59c-afe6-4e46-b3c9-9f2ee741fb62",
            "tabName" : "Carts",
            "tabKey" : "tab2",
            "locked" : false,
            "allowGuestUser" : false,
            "seedComponents" : [ {
              "fqn" : "forceCommunity:relatedList",
              "attributes" : {
                "parentRecordId" : "{!CurrentUser.effectiveAccountId}",
                "relatedListName" : "Carts",
                "showCustomTitle" : "false",
                "showBreadCrumbs" : "false",
                "showRowNumbers" : "false",
                "showManualRefreshButton" : "false"
              }
            } ]
          } ]
        }
      },
      "componentName" : "forceCommunity:tabset",
      "id" : "b60a29ee-39cf-4be1-9054-9ba95c439c34",
      "regions" : [ {
        "components" : [ {
          "componentAttributes" : {
            "customTitle" : "Members",
            "parentRecordId" : "{!CurrentUser.effectiveAccountId}",
            "relatedListName" : "Users",
            "showBreadCrumbs" : false,
            "showCustomTitle" : true,
            "showManualRefreshButton" : false,
            "showRowNumbers" : false
          },
          "componentName" : "forceCommunity:relatedList",
          "id" : "e492a43b-ba90-477c-8d01-de6dadd79677",
          "renditionMap" : { },
          "type" : "component"
        } ],
        "id" : "38225c3a-21eb-4b67-b93b-0dd6ce20555e",
        "regionLabel" : "Members",
        "regionName" : "tab1",
        "renditionMap" : { },
        "type" : "region"
      }, {
        "components" : [ {
          "componentAttributes" : {
            "customTitle" : "",
            "parentRecordId" : "{!CurrentUser.effectiveAccountId}",
            "relatedListName" : "Carts",
            "showBreadCrumbs" : false,
            "showCustomTitle" : false,
            "showManualRefreshButton" : false,
            "showRowNumbers" : false
          },
          "componentName" : "forceCommunity:relatedList",
          "id" : "db3687ba-4f19-4dbb-8556-f4e650e41f25",
          "renditionMap" : { },
          "type" : "component"
        } ],
        "id" : "4c6fb59c-afe6-4e46-b3c9-9f2ee741fb62",
        "regionLabel" : "Carts",
        "regionName" : "tab2",
        "renditionMap" : { },
        "type" : "region"
      } ],
      "renderPriority" : "NEUTRAL",
      "renditionMap" : { },
      "type" : "component"
    } ],
    "id" : "710c7060-2ece-4b6d-b75a-a54769d0f2b3",
    "regionName" : "content",
    "type" : "region"
  }, {
    "id" : "bb942231-bcbe-4b37-bbb9-9ad3c2c52342",
    "regionName" : "footer",
    "type" : "region"
  }, {
    "components" : [ {
      "componentAttributes" : {
        "description" : "",
        "metaTags" : "",
        "title" : "Account Management"
      },
      "componentName" : "forceCommunity:seoAssistant",
      "id" : "7bb7d113-fa99-433c-ba3f-a9a1237ade59",
      "renditionMap" : { },
      "type" : "component"
    } ],
    "id" : "31939138-0c69-4be4-a5a6-e3f80e4ea0cc",
    "regionName" : "sfdcHiddenRegion",
    "type" : "region"
  } ],
  "themeLayoutType" : "Inner",
  "type" : "view",
  "viewType" : "account-management"
}